decomp/__init__.py
decomp/corpus/__init__.py
decomp/corpus/corpus.py
decomp/data/LICENSE
decomp/data/build.log
decomp/data/ud_ids.json
decomp/data/1.0/normalized/sentence/annotations/factuality.zip
decomp/data/1.0/normalized/sentence/annotations/genericity.zip
decomp/data/1.0/normalized/sentence/annotations/protoroles.zip
decomp/data/1.0/normalized/sentence/annotations/time.zip
decomp/data/1.0/normalized/sentence/annotations/wordsense.zip
decomp/data/1.0/raw/sentence/annotations/factuality.zip
decomp/data/1.0/raw/sentence/annotations/genericity.zip
decomp/data/1.0/raw/sentence/annotations/protoroles.zip
decomp/data/1.0/raw/sentence/annotations/time.zip
decomp/data/1.0/raw/sentence/annotations/wordsense.zip
decomp/data/2.0/normalized/document/uds-ewt-documents-dev-normalized.json
decomp/data/2.0/normalized/document/uds-ewt-documents-test-normalized.json
decomp/data/2.0/normalized/document/uds-ewt-documents-train-normalized.json
decomp/data/2.0/normalized/document/annotations/event_structure_mereology.json
decomp/data/2.0/normalized/document/annotations/event_structure_mereology.zip
decomp/data/2.0/normalized/sentence/uds-ewt-sentences-dev-normalized.json
decomp/data/2.0/normalized/sentence/uds-ewt-sentences-test-normalized.json
decomp/data/2.0/normalized/sentence/uds-ewt-sentences-train-normalized.json
decomp/data/2.0/normalized/sentence/annotations/event_structure_distributivity.json
decomp/data/2.0/normalized/sentence/annotations/event_structure_distributivity.zip
decomp/data/2.0/normalized/sentence/annotations/event_structure_natural_parts.json
decomp/data/2.0/normalized/sentence/annotations/event_structure_natural_parts.zip
decomp/data/2.0/normalized/sentence/annotations/factuality.json
decomp/data/2.0/normalized/sentence/annotations/factuality.zip
decomp/data/2.0/normalized/sentence/annotations/genericity.json
decomp/data/2.0/normalized/sentence/annotations/genericity.zip
decomp/data/2.0/normalized/sentence/annotations/protoroles.json
decomp-0.3.2.dist-info/licenses/LICENSE
decomp-0.3.2.dist-info/METADATA
decomp-0.3.2.dist-info/WHEEL
decomp-0.3.2.dist-info/top_level.txt
decomp-0.3.2.dist-info/RECORD
