Metadata-Version: 2.4
Name: decomp
Version: 0.3.2
Summary: Toolkit for working with Universal Decompositional Semantics graphs
Author-email: Aaron Steven White <aaron.white@rochester.edu>
License: MIT
Project-URL: Homepage, https://decomp.io/
Project-URL: Repository, https://github.com/decompositional-semantics-initiative/decomp
Classifier: Development Status :: 4 - Beta
Classifier: Intended Audience :: Science/Research
Classifier: License :: OSI Approved :: MIT License
Classifier: Programming Language :: Python :: 3
Classifier: Programming Language :: Python :: 3.12
Classifier: Topic :: Scientific/Engineering :: Artificial Intelligence
Classifier: Topic :: Text Processing :: Linguistic
Requires-Python: >=3.12
License-File: LICENSE
Requires-Dist: networkx>=2.7.1
Requires-Dist: overrides>=7.0.0
Requires-Dist: rdflib>=7.0.0
Requires-Dist: numpy>=1.24.0
Requires-Dist: pyparsing>=3.0.0
Requires-Dist: requests>=2.31.0
Requires-Dist: termcolor>=2.0.0
Requires-Dist: tabulate>=0.9.0
Provides-Extra: dev
Requires-Dist: pytest>=8.0.0; extra == "dev"
Requires-Dist: pytest-cov>=4.0.0; extra == "dev"
Requires-Dist: ruff>=0.12.0; extra == "dev"
Requires-Dist: mypy>=1.17.0; extra == "dev"
Requires-Dist: types-requests>=2.31.0; extra == "dev"
Requires-Dist: types-tabulate>=0.9.0; extra == "dev"
Requires-Dist: tabulate>=0.9.0; extra == "dev"
Requires-Dist: dash>=2.15.0; extra == "dev"
Requires-Dist: selenium>=4.6.1; extra == "dev"
Requires-Dist: jsonpickle>=1.4.1; extra == "dev"
Requires-Dist: matplotlib>=3.2.1; extra == "dev"
Requires-Dist: concrete>=4.12.0; extra == "dev"
Provides-Extra: viz
Requires-Dist: dash>=2.15.0; extra == "viz"
Requires-Dist: selenium>=4.6.1; extra == "viz"
Requires-Dist: jsonpickle>=1.4.1; extra == "viz"
Requires-Dist: matplotlib>=3.2.1; extra == "viz"
Provides-Extra: parsing
Requires-Dist: concrete>=4.12.0; extra == "parsing"
Dynamic: license-file
